MANIFEST.in
README.md
RELEASE
mmint
setup.py
Mmint/CGratio.py
Mmint/DepthvsReadsNum.py
Mmint/Format.py
Mmint/Genome_fasta.py
Mmint/HistonePeaks.py
Mmint/Meth2ChIP.py
Mmint/MethvsExpression.py
Mmint/OnlineAna.py
Mmint/PCAmeth.py
Mmint/UMRsCompare.py
Mmint/UMRsExplain.py
Mmint/__init__.py
Mmint/annotate.py
Mmint/chartReport.py
Mmint/cluster.py
Mmint/david.pl
Mmint/david.pm
Mmint/ensemblGene.v3.geneSymbolToId
Mmint/horizonalHeatmap.py
Mmint/mCor.py
Mmint/main.py
Mmint/mdepth.py
Mmint/merge.pl
Mmint/merge.py
Mmint/multiBw2Bed.py
Mmint/multiTracks.meth.py
Mmint/multiTracks.py
Mmint/multiTracksmeth.py
Mmint/scatter3d.py
Mmint/ucsc.py
Mmint/ucsc_tracks.pl
Mmint/utils.py
Mmint/volcano.py
Mmint.egg-info/PKG-INFO
Mmint.egg-info/SOURCES.txt
Mmint.egg-info/dependency_links.txt
Mmint.egg-info/requires.txt
Mmint.egg-info/top_level.txt
Mmint/BED/hg19.tss.bed
Mmint/BED/mm10.tss.bed