Metadata-Version: 1.2
Name: Mmint
Version: 0.0.1.9
Summary: Methylation data mining tools
Home-page: https://github.com/lijiacd985/Mmint
Author: Jia Li
Author-email: jiali@tamu.edu
Maintainer: Deqiang Sun
Maintainer-email: dsun@tamu.edu
License: MIT
Platform: all
